packetsocket/__init__.py
packetsocket/packetsocket.py
packetsocket-1.0.0.dist-info/METADATA
packetsocket-1.0.0.dist-info/WHEEL
packetsocket-1.0.0.dist-info/top_level.txt
packetsocket-1.0.0.dist-info/RECORD
