Metadata-Version: 2.1
Name: packetsocket
Version: 1.0.0
Summary: High-level socket interface for non-blocking packet communication
Home-page: https://github.com/Dead-Man-Walker/python-packetsocket
Author: Kevin Hambrecht
Author-email: kev.hambrecht@gmail.com
License: Nope
Platform: UNKNOWN
